Ksana/__init__.py
Ksana/baseserver.py
Ksana/blueprint.py
Ksana/cookies.py
Ksana/errors.py
Ksana/ksana.py
Ksana/request.py
Ksana/response.py
Ksana/route.py
Ksana/session.py
ksana-0.0.2.2.dist-info/DESCRIPTION.rst
ksana-0.0.2.2.dist-info/METADATA
ksana-0.0.2.2.dist-info/RECORD
ksana-0.0.2.2.dist-info/WHEEL
ksana-0.0.2.2.dist-info/metadata.json
ksana-0.0.2.2.dist-info/top_level.txt
