Metadata-Version: 2.0
Name: ksana
Version: 0.0.2.2
Summary: A sample Python web framework
Home-page: https://github.com/zhangguyu6/ksana
Author: Guyu Zhang
Author-email: zhangguyu6@gmail.com
License: MIT
Keywords: sample web asyncio framework
Platform: UNKNOWN
Classifier: Development Status :: 3 - Alpha
Classifier: Environment :: Web Environment
Classifier: License :: OSI Approved :: MIT License
Classifier: Programming Language :: Python :: 3.5
Classifier: Programming Language :: Python :: 3.6
Requires-Dist: httptools (>=0.0.9)
